rebhelp/__init__.py
rebhelp/orbit.py
rebhelp/simgen.py
rebhelp/units.py
rebhelp-0.2.0.dist-info/licenses/LICENSE
rebhelp-0.2.0.dist-info/METADATA
rebhelp-0.2.0.dist-info/WHEEL
rebhelp-0.2.0.dist-info/top_level.txt
rebhelp-0.2.0.dist-info/RECORD
